spotdipy-0.0.7.dist-info/RECORD
spotdipy-0.0.7.dist-info/LICENSE.txt
spotdipy-0.0.7.dist-info/METADATA
spotdipy-0.0.7.dist-info/WHEEL
spotdipy-0.0.7.dist-info/top_level.txt
SpotDIPy/main.py
SpotDIPy/__init__.py
SpotDIPy/cutils.cpython-310-x86_64-linux-gnu.so
SpotDIPy/main-2.py
SpotDIPy/plot_GUI.py
SpotDIPy/utils.py
SpotDIPy/setup.py
SpotDIPy/main_example.py
SpotDIPy/cutils.c
SpotDIPy/SpotDIPy.py
SpotDIPy/main_meeting.py
SpotDIPy/version.py
SpotDIPy/cutils.pyx
SpotDIPy/main_for_project.py
