Metadata-Version: 2.2
Name: SpotDIPy
Version: 0.0.7
Summary: An Easy Way for Stellar Doppler Imaging of Cool Single Stars
Home-page: https://github.com/EnginBahar/SpotDIPy
Author: Engin Bahar
Author-email: enbahar@ankara.edu.tr
Project-URL: Homepage, https://github.com/EnginBahar/SpotDIPy
Project-URL: Issues, https://github.com/EnginBahar/SpotDIPy/issues
Classifier: Programming Language :: Python :: 3
Classifier: License :: OSI Approved :: GNU General Public License v3 (GPLv3)
Classifier: Operating System :: Microsoft :: Windows
Classifier: Operating System :: POSIX :: Linux
Requires-Python: >=3.8
License-File: LICENSE.txt
Requires-Dist: numpy
Requires-Dist: scipy
Requires-Dist: Cython
Requires-Dist: matplotlib
Requires-Dist: basemap
Requires-Dist: astropy
Requires-Dist: PyAstronomy
Requires-Dist: exotic_ld
Requires-Dist: PyDynamic
Requires-Dist: tqdm
Requires-Dist: PyQt5
Requires-Dist: PyQt5-Qt!=5.15.14
Requires-Dist: phoebe
Requires-Dist: kneebow
Requires-Dist: traits
Requires-Dist: traitsui
Requires-Dist: vtk==9.3.0
Requires-Dist: configobj
Requires-Dist: jax
Requires-Dist: jaxopt
Requires-Dist: healpy; platform_system == "Linux"
Dynamic: author
Dynamic: author-email
Dynamic: classifier
Dynamic: description
Dynamic: description-content-type
Dynamic: home-page
Dynamic: project-url
Dynamic: requires-dist
Dynamic: requires-python
Dynamic: summary
